figurestream/__init__.py
figurestream-1.2.8.dist-info/LICENSE
figurestream-1.2.8.dist-info/METADATA
figurestream-1.2.8.dist-info/WHEEL
figurestream-1.2.8.dist-info/top_level.txt
figurestream-1.2.8.dist-info/RECORD
